soll/api.py
soll-0.2.0.dist-info/LICENSE
soll-0.2.0.dist-info/METADATA
soll-0.2.0.dist-info/WHEEL
soll-0.2.0.dist-info/top_level.txt
soll-0.2.0.dist-info/RECORD
